ebcpy/__init__.py
ebcpy/data_types.py
ebcpy/optimization.py
ebcpy/preprocessing.py
ebcpy/modelica/__init__.py
ebcpy/modelica/manipulate_ds.py
ebcpy/modelica/simres.py
ebcpy/simulationapi/__init__.py
ebcpy/simulationapi/dymola_api.py
ebcpy/simulationapi/fmu.py
ebcpy/utils/__init__.py
ebcpy/utils/conversion.py
ebcpy/utils/reproduction.py
ebcpy/utils/statistics_analyzer.py
ebcpy-0.6.1.dist-info/licenses/LICENSE
ebcpy-0.6.1.dist-info/METADATA
ebcpy-0.6.1.dist-info/WHEEL
ebcpy-0.6.1.dist-info/top_level.txt
ebcpy-0.6.1.dist-info/RECORD
