Metadata-Version: 2.4
Name: ebcpy
Version: 0.6.1
Summary: Python Library used for different python modules for the analysis and optimization of energy systems, buildings and indoor climate 
Home-page: https://github.com/RWTH-EBC/ebcpy
Download-URL: https://github.com/RWTH-EBC/ebcpy/archive/refs/tags/0.6.1.tar.gz
Author: RWTH Aachen University, E.ON Energy Research Center, Institute of Energy Efficient Buildings and Indoor Climate
Author-email: fabian.wuellhorst@eonerc.rwth-aachen.de
License: BSD 3-Clause
Keywords: simulation,building,energy,time-series-data,comfort,black-box optimization
Classifier: Development Status :: 3 - Alpha
Classifier: License :: OSI Approved :: BSD License
Classifier: Topic :: Scientific/Engineering
Classifier: Intended Audience :: Science/Research
Classifier: Programming Language :: Python :: 3.7
Classifier: Programming Language :: Python :: 3.8
Classifier: Programming Language :: Python :: 3.9
License-File: LICENSE
Requires-Dist: numpy<2.0,>=1.19.5
Requires-Dist: matplotlib>=3.3.4
Requires-Dist: scipy>=1.5.4
Requires-Dist: pandas>=1.1.5
Requires-Dist: scikit-learn>=0.24.2
Requires-Dist: fmpy<0.3.17,>=0.2.27
Requires-Dist: pydantic>=2.0
Requires-Dist: h5py>=3.1.0
Requires-Dist: tables>=3.6.1
Provides-Extra: full
Requires-Dist: openpyxl>=3.0.5; extra == "full"
Requires-Dist: xlrd>=2.0.1; extra == "full"
Requires-Dist: pymoo==0.5.0; extra == "full"
Requires-Dist: bayesian-optimization==1.4.3; extra == "full"
Requires-Dist: GitPython>=3.1.27; extra == "full"
Requires-Dist: pyarrow>=11.0.0; extra == "full"
Requires-Dist: fastparquet>=2023.1.0; extra == "full"
Dynamic: author
Dynamic: author-email
Dynamic: classifier
Dynamic: description
Dynamic: description-content-type
Dynamic: download-url
Dynamic: home-page
Dynamic: keywords
Dynamic: license
Dynamic: license-file
Dynamic: provides-extra
Dynamic: requires-dist
Dynamic: summary
